healthcare_edi_converter/__init__.py
healthcare_edi_converter/convert837.py
healthcare_edi_converter/convert_base.py
healthcare_edi_converter/converter.py
healthcare_edi_converter/utils.py
healthcare_edi_converter/generate_837/__init__.py
healthcare_edi_converter/generate_837/elements.py
healthcare_edi_converter/generate_837/loops.py
healthcare_edi_converter/generate_837/segments.py
healthcare_edi_converter/models/__init__.py
healthcare_edi_converter/models/claim_dto.py
healthcare_edi_converter/parse_837/__init__.py
healthcare_edi_converter/parse_837/elements/__init__.py
healthcare_edi_converter/parse_837/elements/adjustment_group_code.py
healthcare_edi_converter/parse_837/elements/adjustment_reason_code.py
healthcare_edi_converter/parse_837/elements/amount_qualifier.py
healthcare_edi_converter/parse_837/elements/authorization_information_qualifier.py
healthcare_edi_converter/parse_837/elements/claim_status.py
healthcare_edi_converter/parse_837/elements/date.py
healthcare_edi_converter/parse_837/elements/date_qualifier.py
healthcare_edi_converter/parse_837/elements/dollars.py
healthcare_edi_converter/parse_837/elements/entity_code.py
healthcare_edi_converter/parse_837/elements/entity_type.py
healthcare_edi_converter/parse_837/elements/identification_code_qualifier.py
healthcare_edi_converter/parse_837/elements/identifier.py
healthcare_edi_converter/parse_837/elements/integer.py
healthcare_edi_converter/parse_837/elements/payment_method.py
healthcare_edi_converter/parse_837/elements/reference_qualifier.py
healthcare_edi_converter/parse_837/elements/service_code.py
healthcare_edi_converter/parse_837/elements/service_modifier.py
healthcare_edi_converter/parse_837/elements/service_qualifier.py
healthcare_edi_converter/parse_837/elements/utilities.py
healthcare_edi_converter/parse_837/loops/__init__.py
healthcare_edi_converter/parse_837/loops/billingprovider.py
healthcare_edi_converter/parse_837/loops/claim.py
healthcare_edi_converter/parse_837/loops/patient.py
healthcare_edi_converter-0.0.4.dist-info/LICENSE
healthcare_edi_converter-0.0.4.dist-info/METADATA
healthcare_edi_converter-0.0.4.dist-info/WHEEL
healthcare_edi_converter-0.0.4.dist-info/top_level.txt
healthcare_edi_converter-0.0.4.dist-info/RECORD
