Metadata-Version: 2.2
Name: healthcare-edi-converter
Version: 0.0.4
Summary: A Python library to convert healthcare edi data (837p Claims etc)
Home-page: https://github.com/CloudFocused/healthcare-edi-converter
Author: CloudFocus.tech
Author-email: "CloudFocus, LLC" <chad@CloudFocus.tech>
License: Copyright (c) 2025 CloudFocus.tech
Project-URL: Homepage, https://www.cloudfocus.tech
Project-URL: Repo, https://github.com/CloudFocused/healthcare-edi-converter
Classifier: Programming Language :: Python :: 3
Classifier: License :: OSI Approved :: MIT License
Classifier: Operating System :: OS Independent
Requires-Python: >=3.12
License-File: LICENSE
Requires-Dist: pandas>=1.3.0
Requires-Dist: fastparquet>=2024.11.0
Requires-Dist: numpy>=2.2.2
Requires-Dist: pyarrow>=19.0.0
Requires-Dist: pyx12>=2.3.3
Requires-Dist: pyparsing>=3.0.0
Dynamic: author
Dynamic: home-page
Dynamic: requires-python
